Metadata-Version: 2.1
Name: mkdocs-embed-external-markdown
Version: 3.0.2
Summary: Mkdocs plugin that allow to inject external markdown or markdown section from given url
Author-email: Stas Yakobov <dev@3os.org>
License: MIT
Project-URL: Source, https://github.com/fire1ce/pypi-test
Keywords: mkdocs,plugin,markdown,external-markdown,embed,external,markdown-section
Classifier: License :: OSI Approved :: MIT License
Classifier: Programming Language :: Python :: 3.9
Requires-Python: >=3.9
License-File: LICENSE.md
Requires-Dist: Jinja2>=3.1.0
Requires-Dist: requests>=2.3.0
Provides-Extra: test
Requires-Dist: pytest>=7.4.3; extra == "test"
Requires-Dist: mkdocs>=1.5.3; extra == "test"
